core.py
excepciones.py
queries.py
test.py
utils.py
agenda_entrenos-0.1.3.dist-info/METADATA
agenda_entrenos-0.1.3.dist-info/WHEEL
agenda_entrenos-0.1.3.dist-info/top_level.txt
agenda_entrenos-0.1.3.dist-info/RECORD
