Metadata-Version: 2.4
Name: agenda-entrenos
Version: 0.1.3
Summary: Una agenda para entrenamientos.
Author-email: Cristian Ruiz <cristian.ruiz@alumni.mondragon.edu>, Alejandro Mata <alejandro.mata@alumni.mondragon.edu>, Unai Alvarez <unai.alvarez@alumni.mondragon.edu>, Eleder Martin <eleder.martin@alumni.mondragon.edu>
License: MIT
Project-URL: Homepage, https://test.pypi.org/project/agenda_entrenos/
Classifier: Programming Language :: Python :: 3
Classifier: Operating System :: OS Independent
Requires-Python: >=3.7
